operator.py
setup.py
micropython_operator.egg-info/PKG-INFO
micropython_operator.egg-info/SOURCES.txt
micropython_operator.egg-info/dependency_links.txt
micropython_operator.egg-info/top_level.txt